tetris/__init__.py
tetris/__main__.py
tetris/app.py
tetris/cli.py
tetris/py.typed
tetromino-0.0.0.dev0.dist-info/WHEEL
tetromino-0.0.0.dev0.dist-info/entry_points.txt
tetromino-0.0.0.dev0.dist-info/METADATA
tetromino-0.0.0.dev0.dist-info/RECORD
