Metadata-Version: 2.4
Name: tetromino
Version: 0.0.0.dev0
Summary: 
Keywords: 
Author: D. Danchev
Author-email: D. Danchev <12420863+danchev@users.noreply.github.com>
License-Expression: GPL-3.0-or-later
Classifier: License :: OSI Approved :: MIT License
Classifier: Development Status :: 4 - Beta
Classifier: Programming Language :: Python
Classifier: Programming Language :: Python :: 3.12
Classifier: Programming Language :: Python :: 3.13
Classifier: Programming Language :: Python :: Implementation :: CPython
Classifier: Programming Language :: Python :: Implementation :: PyPy
Requires-Python: >=3.12
Project-URL: Documentation, https://github.com/danchev/tetromino#readme
Project-URL: Issues, https://github.com/danchev/tetromino/issues
Project-URL: Source, https://github.com/danchev/tetromino
